lvtab.py
lvtab-0.0.1.dist-info/LICENSE.txt
lvtab-0.0.1.dist-info/METADATA
lvtab-0.0.1.dist-info/WHEEL
lvtab-0.0.1.dist-info/entry_points.txt
lvtab-0.0.1.dist-info/top_level.txt
lvtab-0.0.1.dist-info/RECORD
